LICENSE.txt
MANIFEST.in
README.txt
TODO.txt
setup.cfg
setup.py
Sanity.egg-info/PKG-INFO
Sanity.egg-info/SOURCES.txt
Sanity.egg-info/dependency_links.txt
Sanity.egg-info/not-zip-safe
Sanity.egg-info/requires.txt
Sanity.egg-info/top_level.txt
contrib/.DS_Store
contrib/fcgi/sanity.fcgi
contrib/fcgi/sanity.nginx.fcgi.conf
contrib/wsgi/gunicorn.conf.py
contrib/wsgi/sanity.nginx.wsgi.conf
contrib/wsgi/sanityapp.py
contrib/wsgi/supervisord.conf
doc/.DS_Store
doc/Makefile
doc/conf.py
doc/index.rst
doc/_build/.DS_Store
doc/_build/doctrees/environment.pickle
doc/_build/doctrees/index.doctree
doc/_build/html/.buildinfo
doc/_build/html/genindex.html
doc/_build/html/index.html
doc/_build/html/objects.inv
doc/_build/html/search.html
doc/_build/html/searchindex.js
doc/_build/html/_sources/index.txt
doc/_build/html/_static/adctheme.css
doc/_build/html/_static/basic.css
doc/_build/html/_static/breadcrumb_background.png
doc/_build/html/_static/doctools.js
doc/_build/html/_static/documentation.png
doc/_build/html/_static/file.png
doc/_build/html/_static/flasky.css
doc/_build/html/_static/header_sm_mid.png
doc/_build/html/_static/jquery.js
doc/_build/html/_static/minus.png
doc/_build/html/_static/mobile.css
doc/_build/html/_static/nature.css
doc/_build/html/_static/plus.png
doc/_build/html/_static/pygments.css
doc/_build/html/_static/sanity.png
doc/_build/html/_static/scrn1.png
doc/_build/html/_static/scrn2.png
doc/_build/html/_static/searchfield_leftcap.png
doc/_build/html/_static/searchfield_repeat.png
doc/_build/html/_static/searchfield_rightcap.png
doc/_build/html/_static/searchtools.js
doc/_build/html/_static/title_background.png
doc/_build/html/_static/toc.js
doc/_build/html/_static/triangle_closed.png
doc/_build/html/_static/triangle_left.png
doc/_build/html/_static/triangle_open.png
doc/_build/html/_static/underscore.js
doc/_build/latex/Makefile
doc/_build/latex/Sanity.aux
doc/_build/latex/Sanity.idx
doc/_build/latex/Sanity.ilg
doc/_build/latex/Sanity.ind
doc/_build/latex/Sanity.log
doc/_build/latex/Sanity.out
doc/_build/latex/Sanity.pdf
doc/_build/latex/Sanity.tex
doc/_build/latex/Sanity.toc
doc/_build/latex/fncychap.sty
doc/_build/latex/python.ist
