Metadata-Version: 1.0
Name: Sanity
Version: 0.2.5
Summary: A team-based task manager intranet application
Home-page: http://bitbucket.org/aaront/sanity/
Author: Aaron Toth
Author-email: atoth89@gmail.com
License: Apache 2.0
Platform: any
Classifier: Development Status :: 3 - Alpha
Classifier: Environment :: Web Environment
Classifier: Intended Audience :: Developers
Classifier: License :: OSI Approved :: Apache Software License
Classifier: Operating System :: OS Independent
Classifier: Programming Language :: Python
Classifier: Topic :: Internet :: WWW/HTTP :: Dynamic Content
